SRC_Endpoints/__init__.py
SRC_Endpoints/announcement_handling.py
SRC_Endpoints/date_handling.py
SRC_Endpoints/effective_volumes.py
SRC_Endpoints/factor_mapping.py
SRC_Endpoints/forecast_flows_handling.py
SRC_Endpoints/name_handling.py
SRC_Endpoints/search_handling.py
SRC_Endpoints/tracking_assumptions.py
SRC_Endpoints/user_handling.py
SRC_Endpoints-0.0.0.2.1.dist-info/LICENSE
SRC_Endpoints-0.0.0.2.1.dist-info/METADATA
SRC_Endpoints-0.0.0.2.1.dist-info/WHEEL
SRC_Endpoints-0.0.0.2.1.dist-info/top_level.txt
SRC_Endpoints-0.0.0.2.1.dist-info/RECORD
