Metadata-Version: 2.1
Name: SRC-Endpoints
Version: 0.0.0.2.1
Summary: A higher level of abstraction around API Endpoints.
Author: Samson Rock Capital
Author-email: david.woroniuk@samsonrock.com
License: MIT
License-File: LICENSE
Requires-Dist: numpy
Requires-Dist: pandas
Requires-Dist: requests
